{
  "description": "LP Sanremo Winter 2025 \u2014 Sanremo",
  "starttime": "2026-03-08",
  "site_name": "pauperwave-2026-03-08-sanremo-winter-2025",
  "source": "pauperwave",
  "format": "pauper",
  "player_count": {},
  "decklists": [
    {
      "player": "Diego Rondini",
      "main_deck": [
        {
          "qty": "4",
          "card_attributes": {
            "card_name": "Voldaren Epicure",
            "card_type": "ISCREA"
          }
        },
        {
          "qty": "4",
          "card_attributes": {
            "card_name": "Kessig Flamebreather",
            "card_type": "ISCREA"
          }
        },
        {
          "qty": "4",
          "card_attributes": {
            "card_name": "Sneaky Snacker",
            "card_type": "ISCREA"
          }
        },
        {
          "qty": "3",
          "card_attributes": {
            "card_name": "Guttersnipe",
            "card_type": "ISCREA"
          }
        },
        {
          "qty": "4",
          "card_attributes": {
            "card_name": "Lava Dart",
            "card_type": "INSTNT"
          }
        },
        {
          "qty": "4",
          "card_attributes": {
            "card_name": "Lightning Bolt",
            "card_type": "INSTNT"
          }
        },
        {
          "qty": "4",
          "card_attributes": {
            "card_name": "Fiery Temper",
            "card_type": "INSTNT"
          }
        },
        {
          "qty": "3",
          "card_attributes": {
            "card_name": "Fireblast",
            "card_type": "INSTNT"
          }
        },
        {
          "qty": "4",
          "card_attributes": {
            "card_name": "Faithless Looting",
            "card_type": "SORCRY"
          }
        },
        {
          "qty": "4",
          "card_attributes": {
            "card_name": "Grab the Prize",
            "card_type": "SORCRY"
          }
        },
        {
          "qty": "4",
          "card_attributes": {
            "card_name": "Highway Robbery",
            "card_type": "SORCRY"
          }
        },
        {
          "qty": "18",
          "card_attributes": {
            "card_name": "Mountain",
            "card_type": "LAND  "
          }
        }
      ],
      "sideboard_deck": [
        {
          "qty": "4",
          "card_attributes": {
            "card_name": "Pyroblast",
            "card_type": "INSTNT"
          }
        },
        {
          "qty": "1",
          "card_attributes": {
            "card_name": "Red Elemental Blast",
            "card_type": "INSTNT"
          }
        },
        {
          "qty": "3",
          "card_attributes": {
            "card_name": "Tectonic Hazard",
            "card_type": "INSTNT"
          }
        },
        {
          "qty": "2",
          "card_attributes": {
            "card_name": "Cast into the Fire",
            "card_type": "INSTNT"
          }
        },
        {
          "qty": "2",
          "card_attributes": {
            "card_name": "Searing Blaze",
            "card_type": "INSTNT"
          }
        },
        {
          "qty": "2",
          "card_attributes": {
            "card_name": "Tormod's Crypt",
            "card_type": "INSTNT"
          }
        },
        {
          "qty": "1",
          "card_attributes": {
            "card_name": "Flaring Pain",
            "card_type": "INSTNT"
          }
        }
      ],
      "archetype": "Red Madness",
      "final_rank": 1,
      "colors": [
        "R"
      ]
    },
    {
      "player": "Andrea Ceravolo",
      "main_deck": [
        {
          "qty": "3",
          "card_attributes": {
            "card_name": "Voldaren Epicure",
            "card_type": "ISCREA"
          }
        },
        {
          "qty": "4",
          "card_attributes": {
            "card_name": "Kessig Flamebreather",
            "card_type": "ISCREA"
          }
        },
        {
          "qty": "4",
          "card_attributes": {
            "card_name": "Sneaky Snacker",
            "card_type": "ISCREA"
          }
        },
        {
          "qty": "4",
          "card_attributes": {
            "card_name": "Guttersnipe",
            "card_type": "ISCREA"
          }
        },
        {
          "qty": "4",
          "card_attributes": {
            "card_name": "Lava Dart",
            "card_type": "INSTNT"
          }
        },
        {
          "qty": "4",
          "card_attributes": {
            "card_name": "Lightning Bolt",
            "card_type": "INSTNT"
          }
        },
        {
          "qty": "2",
          "card_attributes": {
            "card_name": "Searing Blaze",
            "card_type": "INSTNT"
          }
        },
        {
          "qty": "2",
          "card_attributes": {
            "card_name": "Fiery Temper",
            "card_type": "INSTNT"
          }
        },
        {
          "qty": "2",
          "card_attributes": {
            "card_name": "Fireblast",
            "card_type": "INSTNT"
          }
        },
        {
          "qty": "2",
          "card_attributes": {
            "card_name": "End the Festivities",
            "card_type": "SORCRY"
          }
        },
        {
          "qty": "2",
          "card_attributes": {
            "card_name": "Faithless Looting",
            "card_type": "SORCRY"
          }
        },
        {
          "qty": "4",
          "card_attributes": {
            "card_name": "Grab the Prize",
            "card_type": "SORCRY"
          }
        },
        {
          "qty": "3",
          "card_attributes": {
            "card_name": "Highway Robbery",
            "card_type": "SORCRY"
          }
        },
        {
          "qty": "1",
          "card_attributes": {
            "card_name": "Tormod's Crypt",
            "card_type": "ARTFCT"
          }
        },
        {
          "qty": "18",
          "card_attributes": {
            "card_name": "Mountain",
            "card_type": "LAND  "
          }
        }
      ],
      "sideboard_deck": [
        {
          "qty": "3",
          "card_attributes": {
            "card_name": "Cast into the Fire",
            "card_type": "INSTNT"
          }
        },
        {
          "qty": "3",
          "card_attributes": {
            "card_name": "Red Elemental Blast",
            "card_type": "INSTNT"
          }
        },
        {
          "qty": "2",
          "card_attributes": {
            "card_name": "Tormod's Crypt",
            "card_type": "INSTNT"
          }
        },
        {
          "qty": "1",
          "card_attributes": {
            "card_name": "End the Festivities",
            "card_type": "INSTNT"
          }
        },
        {
          "qty": "1",
          "card_attributes": {
            "card_name": "Faithless Looting",
            "card_type": "INSTNT"
          }
        },
        {
          "qty": "1",
          "card_attributes": {
            "card_name": "Fiery Temper",
            "card_type": "INSTNT"
          }
        },
        {
          "qty": "1",
          "card_attributes": {
            "card_name": "Fireblast",
            "card_type": "INSTNT"
          }
        },
        {
          "qty": "1",
          "card_attributes": {
            "card_name": "Highway Robbery",
            "card_type": "INSTNT"
          }
        },
        {
          "qty": "1",
          "card_attributes": {
            "card_name": "Searing Blaze",
            "card_type": "INSTNT"
          }
        },
        {
          "qty": "1",
          "card_attributes": {
            "card_name": "Voldaren Epicure",
            "card_type": "INSTNT"
          }
        }
      ],
      "archetype": "R Madness",
      "final_rank": 2,
      "colors": [
        "R"
      ]
    },
    {
      "player": "Cristian Cricco",
      "main_deck": [
        {
          "qty": "4",
          "card_attributes": {
            "card_name": "Arbor Elf",
            "card_type": "ISCREA"
          }
        },
        {
          "qty": "1",
          "card_attributes": {
            "card_name": "Elvish Mystic",
            "card_type": "ISCREA"
          }
        },
        {
          "qty": "3",
          "card_attributes": {
            "card_name": "Llanowar Elves",
            "card_type": "ISCREA"
          }
        },
        {
          "qty": "4",
          "card_attributes": {
            "card_name": "Quirion Ranger",
            "card_type": "ISCREA"
          }
        },
        {
          "qty": "2",
          "card_attributes": {
            "card_name": "Masked Vandal",
            "card_type": "ISCREA"
          }
        },
        {
          "qty": "4",
          "card_attributes": {
            "card_name": "Priest of Titania",
            "card_type": "ISCREA"
          }
        },
        {
          "qty": "3",
          "card_attributes": {
            "card_name": "Vitu-Ghazi Inspector",
            "card_type": "ISCREA"
          }
        },
        {
          "qty": "2",
          "card_attributes": {
            "card_name": "Wellwisher",
            "card_type": "ISCREA"
          }
        },
        {
          "qty": "4",
          "card_attributes": {
            "card_name": "Timberwatch Elf",
            "card_type": "ISCREA"
          }
        },
        {
          "qty": "4",
          "card_attributes": {
            "card_name": "Sagu Wildling // Roost Seek",
            "card_type": "ISCREA"
          }
        },
        {
          "qty": "4",
          "card_attributes": {
            "card_name": "Generous Ent",
            "card_type": "ISCREA"
          }
        },
        {
          "qty": "4",
          "card_attributes": {
            "card_name": "Nyxborn Hydra",
            "card_type": "ISCREA"
          }
        },
        {
          "qty": "2",
          "card_attributes": {
            "card_name": "Land Grant",
            "card_type": "SORCRY"
          }
        },
        {
          "qty": "4",
          "card_attributes": {
            "card_name": "Winding Way",
            "card_type": "SORCRY"
          }
        },
        {
          "qty": "4",
          "card_attributes": {
            "card_name": "Lead the Stampede",
            "card_type": "SORCRY"
          }
        },
        {
          "qty": "1",
          "card_attributes": {
            "card_name": "Gingerbread Cabin",
            "card_type": "LAND  "
          }
        },
        {
          "qty": "10",
          "card_attributes": {
            "card_name": "Forest",
            "card_type": "LAND  "
          }
        }
      ],
      "sideboard_deck": [
        {
          "qty": "2",
          "card_attributes": {
            "card_name": "Blue Elemental Blast",
            "card_type": "INSTNT"
          }
        },
        {
          "qty": "2",
          "card_attributes": {
            "card_name": "Hydroblast",
            "card_type": "INSTNT"
          }
        },
        {
          "qty": "4",
          "card_attributes": {
            "card_name": "Monstrous Emergence",
            "card_type": "INSTNT"
          }
        },
        {
          "qty": "2",
          "card_attributes": {
            "card_name": "Faerie Macabre",
            "card_type": "INSTNT"
          }
        },
        {
          "qty": "2",
          "card_attributes": {
            "card_name": "Masked Vandal",
            "card_type": "INSTNT"
          }
        },
        {
          "qty": "1",
          "card_attributes": {
            "card_name": "Island",
            "card_type": "INSTNT"
          }
        },
        {
          "qty": "1",
          "card_attributes": {
            "card_name": "Spinewoods Paladin",
            "card_type": "INSTNT"
          }
        },
        {
          "qty": "1",
          "card_attributes": {
            "card_name": "Tangled Islet",
            "card_type": "INSTNT"
          }
        }
      ],
      "archetype": "Elves",
      "final_rank": 3,
      "colors": [
        "G",
        "U"
      ]
    },
    {
      "player": "Andrea Oddone",
      "main_deck": [
        {
          "qty": "2",
          "card_attributes": {
            "card_name": "Brinebarrow Intruder",
            "card_type": "ISCREA"
          }
        },
        {
          "qty": "4",
          "card_attributes": {
            "card_name": "Faerie Seer",
            "card_type": "ISCREA"
          }
        },
        {
          "qty": "2",
          "card_attributes": {
            "card_name": "Harrier Strix",
            "card_type": "ISCREA"
          }
        },
        {
          "qty": "2",
          "card_attributes": {
            "card_name": "Humbling Elder",
            "card_type": "ISCREA"
          }
        },
        {
          "qty": "4",
          "card_attributes": {
            "card_name": "Illvoi Galeblade",
            "card_type": "ISCREA"
          }
        },
        {
          "qty": "1",
          "card_attributes": {
            "card_name": "Snaremaster Sprite",
            "card_type": "ISCREA"
          }
        },
        {
          "qty": "4",
          "card_attributes": {
            "card_name": "Moon-Circuit Hacker",
            "card_type": "ISCREA"
          }
        },
        {
          "qty": "4",
          "card_attributes": {
            "card_name": "Spellstutter Sprite",
            "card_type": "ISCREA"
          }
        },
        {
          "qty": "4",
          "card_attributes": {
            "card_name": "Ninja of the Deep Hours",
            "card_type": "ISCREA"
          }
        },
        {
          "qty": "4",
          "card_attributes": {
            "card_name": "Spell Pierce",
            "card_type": "INSTNT"
          }
        },
        {
          "qty": "4",
          "card_attributes": {
            "card_name": "Counterspell",
            "card_type": "INSTNT"
          }
        },
        {
          "qty": "3",
          "card_attributes": {
            "card_name": "Snap",
            "card_type": "INSTNT"
          }
        },
        {
          "qty": "4",
          "card_attributes": {
            "card_name": "Of One Mind",
            "card_type": "SORCRY"
          }
        },
        {
          "qty": "1",
          "card_attributes": {
            "card_name": "Lonely Sandbar",
            "card_type": "LAND  "
          }
        },
        {
          "qty": "17",
          "card_attributes": {
            "card_name": "Island",
            "card_type": "LAND  "
          }
        }
      ],
      "sideboard_deck": [
        {
          "qty": "4",
          "card_attributes": {
            "card_name": "Cryoshatter",
            "card_type": "INSTNT"
          }
        },
        {
          "qty": "2",
          "card_attributes": {
            "card_name": "Blue Elemental Blast",
            "card_type": "INSTNT"
          }
        },
        {
          "qty": "2",
          "card_attributes": {
            "card_name": "Hydroblast",
            "card_type": "INSTNT"
          }
        },
        {
          "qty": "2",
          "card_attributes": {
            "card_name": "Annul",
            "card_type": "INSTNT"
          }
        },
        {
          "qty": "2",
          "card_attributes": {
            "card_name": "Tormod's Crypt",
            "card_type": "INSTNT"
          }
        },
        {
          "qty": "2",
          "card_attributes": {
            "card_name": "Unable to Scream",
            "card_type": "INSTNT"
          }
        },
        {
          "qty": "1",
          "card_attributes": {
            "card_name": "Steel Sabotage",
            "card_type": "INSTNT"
          }
        }
      ],
      "archetype": "U Faeries",
      "final_rank": 3,
      "colors": [
        "U"
      ]
    },
    {
      "player": "Mirko Crisci",
      "main_deck": [
        {
          "qty": "2",
          "card_attributes": {
            "card_name": "Elves of Deep Shadow",
            "card_type": "ISCREA"
          }
        },
        {
          "qty": "4",
          "card_attributes": {
            "card_name": "Saruli Caretaker",
            "card_type": "ISCREA"
          }
        },
        {
          "qty": "4",
          "card_attributes": {
            "card_name": "Gatecreeper Vine",
            "card_type": "ISCREA"
          }
        },
        {
          "qty": "2",
          "card_attributes": {
            "card_name": "Masked Vandal",
            "card_type": "ISCREA"
          }
        },
        {
          "qty": "2",
          "card_attributes": {
            "card_name": "Mesmeric Fiend",
            "card_type": "ISCREA"
          }
        },
        {
          "qty": "4",
          "card_attributes": {
            "card_name": "Overgrown Battlement",
            "card_type": "ISCREA"
          }
        },
        {
          "qty": "4",
          "card_attributes": {
            "card_name": "Wall of Roots",
            "card_type": "ISCREA"
          }
        },
        {
          "qty": "4",
          "card_attributes": {
            "card_name": "Balustrade Spy",
            "card_type": "ISCREA"
          }
        },
        {
          "qty": "4",
          "card_attributes": {
            "card_name": "Sagu Wildling // Roost Seek",
            "card_type": "ISCREA"
          }
        },
        {
          "qty": "4",
          "card_attributes": {
            "card_name": "Generous Ent",
            "card_type": "ISCREA"
          }
        },
        {
          "qty": "2",
          "card_attributes": {
            "card_name": "Troll of Khazad-d\u00fbm",
            "card_type": "ISCREA"
          }
        },
        {
          "qty": "2",
          "card_attributes": {
            "card_name": "Lotleth Giant",
            "card_type": "ISCREA"
          }
        },
        {
          "qty": "1",
          "card_attributes": {
            "card_name": "Elven Farsight",
            "card_type": "SORCRY"
          }
        },
        {
          "qty": "4",
          "card_attributes": {
            "card_name": "Land Grant",
            "card_type": "SORCRY"
          }
        },
        {
          "qty": "4",
          "card_attributes": {
            "card_name": "Winding Way",
            "card_type": "SORCRY"
          }
        },
        {
          "qty": "3",
          "card_attributes": {
            "card_name": "Lead the Stampede",
            "card_type": "SORCRY"
          }
        },
        {
          "qty": "2",
          "card_attributes": {
            "card_name": "Dread Return",
            "card_type": "SORCRY"
          }
        },
        {
          "qty": "4",
          "card_attributes": {
            "card_name": "Lotus Petal",
            "card_type": "ARTFCT"
          }
        },
        {
          "qty": "3",
          "card_attributes": {
            "card_name": "Forest",
            "card_type": "LAND  "
          }
        },
        {
          "qty": "1",
          "card_attributes": {
            "card_name": "Swamp",
            "card_type": "LAND  "
          }
        }
      ],
      "sideboard_deck": [
        {
          "qty": "4",
          "card_attributes": {
            "card_name": "Healer of the Glade",
            "card_type": "INSTNT"
          }
        },
        {
          "qty": "3",
          "card_attributes": {
            "card_name": "Scattershot Archer",
            "card_type": "INSTNT"
          }
        },
        {
          "qty": "2",
          "card_attributes": {
            "card_name": "Masked Vandal",
            "card_type": "INSTNT"
          }
        },
        {
          "qty": "2",
          "card_attributes": {
            "card_name": "Mesmeric Fiend",
            "card_type": "INSTNT"
          }
        },
        {
          "qty": "2",
          "card_attributes": {
            "card_name": "Vitu-Ghazi Inspector",
            "card_type": "INSTNT"
          }
        },
        {
          "qty": "1",
          "card_attributes": {
            "card_name": "Flaring Pain",
            "card_type": "INSTNT"
          }
        },
        {
          "qty": "1",
          "card_attributes": {
            "card_name": "Swamp",
            "card_type": "INSTNT"
          }
        }
      ],
      "archetype": "Spy",
      "final_rank": 5,
      "colors": [
        "B",
        "G"
      ]
    },
    {
      "player": "Alessandro Franzone",
      "main_deck": [
        {
          "qty": "4",
          "card_attributes": {
            "card_name": "Arbor Elf",
            "card_type": "ISCREA"
          }
        },
        {
          "qty": "4",
          "card_attributes": {
            "card_name": "Eldrazi Repurposer",
            "card_type": "ISCREA"
          }
        },
        {
          "qty": "2",
          "card_attributes": {
            "card_name": "Evolution Witness",
            "card_type": "ISCREA"
          }
        },
        {
          "qty": "4",
          "card_attributes": {
            "card_name": "Jewel Thief",
            "card_type": "ISCREA"
          }
        },
        {
          "qty": "3",
          "card_attributes": {
            "card_name": "Bannerhide Krushok",
            "card_type": "ISCREA"
          }
        },
        {
          "qty": "4",
          "card_attributes": {
            "card_name": "Writhing Chrysalis",
            "card_type": "ISCREA"
          }
        },
        {
          "qty": "4",
          "card_attributes": {
            "card_name": "Avenging Hunter",
            "card_type": "ISCREA"
          }
        },
        {
          "qty": "3",
          "card_attributes": {
            "card_name": "Nyxborn Hydra",
            "card_type": "ISCREA"
          }
        },
        {
          "qty": "2",
          "card_attributes": {
            "card_name": "Ram Through",
            "card_type": "INSTNT"
          }
        },
        {
          "qty": "4",
          "card_attributes": {
            "card_name": "Malevolent Rumble",
            "card_type": "SORCRY"
          }
        },
        {
          "qty": "2",
          "card_attributes": {
            "card_name": "You Meet in a Tavern",
            "card_type": "SORCRY"
          }
        },
        {
          "qty": "4",
          "card_attributes": {
            "card_name": "Utopia Sprawl",
            "card_type": "ENCHMN"
          }
        },
        {
          "qty": "4",
          "card_attributes": {
            "card_name": "Wild Growth",
            "card_type": "ENCHMN"
          }
        },
        {
          "qty": "14",
          "card_attributes": {
            "card_name": "Forest",
            "card_type": "LAND  "
          }
        },
        {
          "qty": "2",
          "card_attributes": {
            "card_name": "Mountain",
            "card_type": "LAND  "
          }
        }
      ],
      "sideboard_deck": [
        {
          "qty": "3",
          "card_attributes": {
            "card_name": "Deglamer",
            "card_type": "INSTNT"
          }
        },
        {
          "qty": "3",
          "card_attributes": {
            "card_name": "Tormod's Crypt",
            "card_type": "INSTNT"
          }
        },
        {
          "qty": "2",
          "card_attributes": {
            "card_name": "Fiery Cannonade",
            "card_type": "INSTNT"
          }
        },
        {
          "qty": "2",
          "card_attributes": {
            "card_name": "Kaervek's Torch",
            "card_type": "INSTNT"
          }
        },
        {
          "qty": "2",
          "card_attributes": {
            "card_name": "Predator's Rapport",
            "card_type": "INSTNT"
          }
        },
        {
          "qty": "2",
          "card_attributes": {
            "card_name": "Ram Through",
            "card_type": "INSTNT"
          }
        },
        {
          "qty": "1",
          "card_attributes": {
            "card_name": "Campfire",
            "card_type": "INSTNT"
          }
        }
      ],
      "archetype": "Monsters",
      "final_rank": 5,
      "colors": [
        "G",
        "R"
      ]
    },
    {
      "player": "Lavinia Cecchi",
      "main_deck": [
        {
          "qty": "4",
          "card_attributes": {
            "card_name": "Delver of Secrets // Insectile Aberration",
            "card_type": "ISCREA"
          }
        },
        {
          "qty": "4",
          "card_attributes": {
            "card_name": "Cryptic Serpent",
            "card_type": "ISCREA"
          }
        },
        {
          "qty": "4",
          "card_attributes": {
            "card_name": "Tolarian Terror",
            "card_type": "ISCREA"
          }
        },
        {
          "qty": "4",
          "card_attributes": {
            "card_name": "Brainstorm",
            "card_type": "INSTNT"
          }
        },
        {
          "qty": "4",
          "card_attributes": {
            "card_name": "Mental Note",
            "card_type": "INSTNT"
          }
        },
        {
          "qty": "2",
          "card_attributes": {
            "card_name": "Spell Pierce",
            "card_type": "INSTNT"
          }
        },
        {
          "qty": "4",
          "card_attributes": {
            "card_name": "Thought Scour",
            "card_type": "INSTNT"
          }
        },
        {
          "qty": "4",
          "card_attributes": {
            "card_name": "Counterspell",
            "card_type": "INSTNT"
          }
        },
        {
          "qty": "1",
          "card_attributes": {
            "card_name": "Unexpected Fangs",
            "card_type": "INSTNT"
          }
        },
        {
          "qty": "2",
          "card_attributes": {
            "card_name": "Suffocating Fumes",
            "card_type": "INSTNT"
          }
        },
        {
          "qty": "2",
          "card_attributes": {
            "card_name": "Artful Dodge",
            "card_type": "SORCRY"
          }
        },
        {
          "qty": "2",
          "card_attributes": {
            "card_name": "Ponder",
            "card_type": "SORCRY"
          }
        },
        {
          "qty": "1",
          "card_attributes": {
            "card_name": "Sleep of the Dead",
            "card_type": "SORCRY"
          }
        },
        {
          "qty": "3",
          "card_attributes": {
            "card_name": "Deem Inferior",
            "card_type": "SORCRY"
          }
        },
        {
          "qty": "4",
          "card_attributes": {
            "card_name": "L\u00f3rien Revealed",
            "card_type": "SORCRY"
          }
        },
        {
          "qty": "3",
          "card_attributes": {
            "card_name": "Contaminated Aquifer",
            "card_type": "LAND  "
          }
        },
        {
          "qty": "12",
          "card_attributes": {
            "card_name": "Island",
            "card_type": "LAND  "
          }
        }
      ],
      "sideboard_deck": [
        {
          "qty": "3",
          "card_attributes": {
            "card_name": "Blue Elemental Blast",
            "card_type": "INSTNT"
          }
        },
        {
          "qty": "2",
          "card_attributes": {
            "card_name": "Hydroblast",
            "card_type": "INSTNT"
          }
        },
        {
          "qty": "2",
          "card_attributes": {
            "card_name": "Annul",
            "card_type": "INSTNT"
          }
        },
        {
          "qty": "2",
          "card_attributes": {
            "card_name": "Cast Down",
            "card_type": "INSTNT"
          }
        },
        {
          "qty": "2",
          "card_attributes": {
            "card_name": "Feed the Swarm",
            "card_type": "INSTNT"
          }
        },
        {
          "qty": "2",
          "card_attributes": {
            "card_name": "Tormod's Crypt",
            "card_type": "INSTNT"
          }
        },
        {
          "qty": "1",
          "card_attributes": {
            "card_name": "Sleep of the Dead",
            "card_type": "INSTNT"
          }
        },
        {
          "qty": "1",
          "card_attributes": {
            "card_name": "Unexpected Fangs",
            "card_type": "INSTNT"
          }
        }
      ],
      "archetype": "UB Terror",
      "final_rank": 5,
      "colors": [
        "B",
        "U"
      ]
    },
    {
      "player": "Nicholas Lanteri",
      "main_deck": [
        {
          "qty": "4",
          "card_attributes": {
            "card_name": "Clockwork Percussionist",
            "card_type": "ISCREA"
          }
        },
        {
          "qty": "4",
          "card_attributes": {
            "card_name": "Goblin Bushwhacker",
            "card_type": "ISCREA"
          }
        },
        {
          "qty": "4",
          "card_attributes": {
            "card_name": "Goblin Tomb Raider",
            "card_type": "ISCREA"
          }
        },
        {
          "qty": "4",
          "card_attributes": {
            "card_name": "Voldaren Epicure",
            "card_type": "ISCREA"
          }
        },
        {
          "qty": "4",
          "card_attributes": {
            "card_name": "Burning-Tree Emissary",
            "card_type": "ISCREA"
          }
        },
        {
          "qty": "4",
          "card_attributes": {
            "card_name": "Galvanic Blast",
            "card_type": "INSTNT"
          }
        },
        {
          "qty": "4",
          "card_attributes": {
            "card_name": "Lightning Bolt",
            "card_type": "INSTNT"
          }
        },
        {
          "qty": "2",
          "card_attributes": {
            "card_name": "Chain Lightning",
            "card_type": "SORCRY"
          }
        },
        {
          "qty": "1",
          "card_attributes": {
            "card_name": "End the Festivities",
            "card_type": "SORCRY"
          }
        },
        {
          "qty": "4",
          "card_attributes": {
            "card_name": "Rally at the Hornburg",
            "card_type": "SORCRY"
          }
        },
        {
          "qty": "4",
          "card_attributes": {
            "card_name": "Wrenn's Resolve",
            "card_type": "SORCRY"
          }
        },
        {
          "qty": "3",
          "card_attributes": {
            "card_name": "Experimental Synthesizer",
            "card_type": "ARTFCT"
          }
        },
        {
          "qty": "4",
          "card_attributes": {
            "card_name": "Great Furnace",
            "card_type": "LAND  "
          }
        },
        {
          "qty": "14",
          "card_attributes": {
            "card_name": "Mountain",
            "card_type": "LAND  "
          }
        }
      ],
      "sideboard_deck": [
        {
          "qty": "4",
          "card_attributes": {
            "card_name": "Red Elemental Blast",
            "card_type": "INSTNT"
          }
        },
        {
          "qty": "3",
          "card_attributes": {
            "card_name": "Cast into the Fire",
            "card_type": "INSTNT"
          }
        },
        {
          "qty": "3",
          "card_attributes": {
            "card_name": "Relic of Progenitus",
            "card_type": "INSTNT"
          }
        },
        {
          "qty": "3",
          "card_attributes": {
            "card_name": "Suplex",
            "card_type": "INSTNT"
          }
        },
        {
          "qty": "2",
          "card_attributes": {
            "card_name": "End the Festivities",
            "card_type": "INSTNT"
          }
        }
      ],
      "archetype": "Rally",
      "final_rank": 5,
      "colors": [
        "R"
      ]
    }
  ]
}