{
  "archetype": "Jund",
  "slug": "jund",
  "stats": {
    "total_entries": 1254,
    "league_entries": 539,
    "league_trophies": 539,
    "league_trophies_yearly": 218,
    "challenge_appearances": 612,
    "challenge_wins": 2476,
    "challenge_losses": 1538,
    "irl_top8": 53,
    "challenge_win_pct": 62,
    "league_trophy_rank_yearly": 5,
    "league_trophy_rank_alltime": 5,
    "league_trophy_decks_yearly": 65,
    "league_trophy_decks_alltime": 71
  },
  "recent_entries": [
    {
      "site_name": "pauper-league-2026-07-1610855",
      "tournament": "Pauper League",
      "date": "2026-07-16",
      "player": "Frecuenza12",
      "colors": [
        "B",
        "G",
        "R"
      ],
      "record": "5-0",
      "final_rank": null,
      "source": "mtgo",
      "type": "league"
    },
    {
      "site_name": "pauper-challenge-32-2026-07-0312847177",
      "tournament": "Pauper Challenge 32",
      "date": "2026-07-15",
      "player": "lilianna1989",
      "colors": [
        "B",
        "G",
        "R"
      ],
      "record": "5-2",
      "final_rank": 7,
      "source": "mtgo",
      "type": "challenge"
    },
    {
      "site_name": "pauper-challenge-32-2026-07-0312847177",
      "tournament": "Pauper Challenge 32",
      "date": "2026-07-15",
      "player": "_blaze66",
      "colors": [
        "B",
        "G",
        "R"
      ],
      "record": "4-2",
      "final_rank": 10,
      "source": "mtgo",
      "type": "challenge"
    },
    {
      "site_name": "pauper-challenge-32-2026-07-1512847177",
      "tournament": "Pauper Challenge 32",
      "date": "2026-07-15",
      "player": "lilianna1989",
      "colors": [
        "B",
        "G",
        "R"
      ],
      "record": "5-2",
      "final_rank": 7,
      "source": "mtgo",
      "type": "challenge"
    },
    {
      "site_name": "pauper-challenge-32-2026-07-1512847177",
      "tournament": "Pauper Challenge 32",
      "date": "2026-07-15",
      "player": "_blaze66",
      "colors": [
        "B",
        "G",
        "R"
      ],
      "record": "4-2",
      "final_rank": 10,
      "source": "mtgo",
      "type": "challenge"
    },
    {
      "site_name": "pauper-league-2026-07-1410855",
      "tournament": "Pauper League",
      "date": "2026-07-14",
      "player": "Yugi_Muto",
      "colors": [
        "B",
        "G",
        "R"
      ],
      "record": "5-0",
      "final_rank": null,
      "source": "mtgo",
      "type": "league"
    },
    {
      "site_name": "pauper-league-2026-07-1410855",
      "tournament": "Pauper League",
      "date": "2026-07-14",
      "player": "Thn",
      "colors": [
        "B",
        "G",
        "R"
      ],
      "record": "5-0",
      "final_rank": null,
      "source": "mtgo",
      "type": "league"
    },
    {
      "site_name": "pauper-league-2026-07-1410855",
      "tournament": "Pauper League",
      "date": "2026-07-14",
      "player": "Oscar_Franco",
      "colors": [
        "B",
        "G",
        "R"
      ],
      "record": "5-0",
      "final_rank": null,
      "source": "mtgo",
      "type": "league"
    },
    {
      "site_name": "pauper-league-2026-07-1310855",
      "tournament": "Pauper League",
      "date": "2026-07-13",
      "player": "_Rogusbr_",
      "colors": [
        "B",
        "G",
        "R"
      ],
      "record": "5-0",
      "final_rank": null,
      "source": "mtgo",
      "type": "league"
    },
    {
      "site_name": "pauper-league-2026-07-1210855",
      "tournament": "Pauper League",
      "date": "2026-07-12",
      "player": "lucotto",
      "colors": [
        "B",
        "G",
        "R"
      ],
      "record": "5-0",
      "final_rank": null,
      "source": "mtgo",
      "type": "league"
    },
    {
      "site_name": "pauper-challenge-32-2026-07-1212847145",
      "tournament": "Pauper Challenge 32",
      "date": "2026-07-12",
      "player": "Brasatore",
      "colors": [
        "B",
        "G",
        "R"
      ],
      "record": "3-3",
      "final_rank": 23,
      "source": "mtgo",
      "type": "challenge"
    },
    {
      "site_name": "pauper-challenge-32-2026-07-1112847128",
      "tournament": "Pauper Challenge 32",
      "date": "2026-07-11",
      "player": "flower270",
      "colors": [
        "B",
        "G",
        "R"
      ],
      "record": "5-3",
      "final_rank": 4,
      "source": "mtgo",
      "type": "challenge"
    },
    {
      "site_name": "pauper-challenge-32-2026-07-1112847128",
      "tournament": "Pauper Challenge 32",
      "date": "2026-07-11",
      "player": "eXeliS",
      "colors": [
        "B",
        "G",
        "R"
      ],
      "record": "3-3",
      "final_rank": 22,
      "source": "mtgo",
      "type": "challenge"
    },
    {
      "site_name": "pauper-challenge-32-2026-07-1112847128",
      "tournament": "Pauper Challenge 32",
      "date": "2026-07-11",
      "player": "_blaze66",
      "colors": [
        "B",
        "G",
        "R"
      ],
      "record": "3-3",
      "final_rank": 25,
      "source": "mtgo",
      "type": "challenge"
    },
    {
      "site_name": "pauper-league-2026-07-1010855",
      "tournament": "Pauper League",
      "date": "2026-07-10",
      "player": "scalo94",
      "colors": [
        "B",
        "G",
        "R"
      ],
      "record": "5-0",
      "final_rank": null,
      "source": "mtgo",
      "type": "league"
    },
    {
      "site_name": "pauper-challenge-32-2026-07-1012847113",
      "tournament": "Pauper Challenge 32",
      "date": "2026-07-10",
      "player": "_blaze66",
      "colors": [
        "B",
        "G",
        "R"
      ],
      "record": "4-2",
      "final_rank": 17,
      "source": "mtgo",
      "type": "challenge"
    },
    {
      "site_name": "pauper-challenge-32-2026-07-0912847103",
      "tournament": "Pauper Challenge 32",
      "date": "2026-07-09",
      "player": "_blaze66",
      "colors": [
        "B",
        "G",
        "R"
      ],
      "record": "7-2",
      "final_rank": 2,
      "source": "mtgo",
      "type": "challenge"
    },
    {
      "site_name": "pauper-challenge-32-2026-07-0912847103",
      "tournament": "Pauper Challenge 32",
      "date": "2026-07-09",
      "player": "outZEROo",
      "colors": [
        "B",
        "G",
        "R"
      ],
      "record": "4-2",
      "final_rank": 12,
      "source": "mtgo",
      "type": "challenge"
    },
    {
      "site_name": "pauper-challenge-32-2026-07-0912847103",
      "tournament": "Pauper Challenge 32",
      "date": "2026-07-09",
      "player": "Yugi_Muto",
      "colors": [
        "B",
        "G",
        "R"
      ],
      "record": "3-3",
      "final_rank": 32,
      "source": "mtgo",
      "type": "challenge"
    },
    {
      "site_name": "pauper-league-2026-07-0910855",
      "tournament": "Pauper League",
      "date": "2026-07-09",
      "player": "newbarola",
      "colors": [
        "B",
        "G",
        "R"
      ],
      "record": "5-0",
      "final_rank": null,
      "source": "mtgo",
      "type": "league"
    },
    {
      "site_name": "pauper-league-2026-07-0810855",
      "tournament": "Pauper League",
      "date": "2026-07-08",
      "player": "Frecuenza12",
      "colors": [
        "B",
        "G",
        "R"
      ],
      "record": "5-0",
      "final_rank": null,
      "source": "mtgo",
      "type": "league"
    },
    {
      "site_name": "pauper-league-2026-07-0810855",
      "tournament": "Pauper League",
      "date": "2026-07-08",
      "player": "SamaLama",
      "colors": [
        "B",
        "G",
        "R"
      ],
      "record": "5-0",
      "final_rank": null,
      "source": "mtgo",
      "type": "league"
    },
    {
      "site_name": "pauper-challenge-32-2026-07-0812846623",
      "tournament": "Pauper Challenge 32",
      "date": "2026-07-08",
      "player": "Minivan_of_Jeskai",
      "colors": [
        "B",
        "G",
        "R"
      ],
      "record": "7-1",
      "final_rank": 3,
      "source": "mtgo",
      "type": "challenge"
    },
    {
      "site_name": "pauper-challenge-32-2026-07-0612846623",
      "tournament": "Pauper Challenge 32",
      "date": "2026-07-08",
      "player": "Minivan_of_Jeskai",
      "colors": [
        "B",
        "G",
        "R"
      ],
      "record": "7-1",
      "final_rank": 3,
      "source": "mtgo",
      "type": "challenge"
    },
    {
      "site_name": "pauper-league-2026-07-0710855",
      "tournament": "Pauper League",
      "date": "2026-07-07",
      "player": "TheValter91",
      "colors": [
        "B",
        "G",
        "R"
      ],
      "record": "5-0",
      "final_rank": null,
      "source": "mtgo",
      "type": "league"
    }
  ],
  "top_pilots": [
    {
      "player": "_blaze66",
      "count": 159
    },
    {
      "player": "Walker735",
      "count": 63
    },
    {
      "player": "seasonofmists",
      "count": 36
    },
    {
      "player": "kuldothared",
      "count": 34
    },
    {
      "player": "Paul16",
      "count": 24
    },
    {
      "player": "wolf777",
      "count": 18
    },
    {
      "player": "SpikeYou",
      "count": 18
    },
    {
      "player": "outZEROo",
      "count": 18
    },
    {
      "player": "AlessandroPiraccini",
      "count": 17
    },
    {
      "player": "yuxiaoyu",
      "count": 17
    }
  ]
}
