{
  "username": "defnot",
  "display_name": "DefNot",
  "irl_name": null,
  "stats": {
    "total_entries": 1,
    "league_trophies": 0,
    "league_trophies_yearly": 0,
    "challenge_wins": 2,
    "challenge_losses": 2,
    "irl_top8": 0,
    "challenge_win_pct": 50,
    "league_trophy_rank_yearly": null,
    "league_trophy_rank_alltime": null,
    "league_trophy_players_yearly": 1154,
    "league_trophy_players_alltime": 1912
  },
  "favorite_decks": [
    {
      "archetype": "White Weenie",
      "count": 1
    }
  ],
  "recent_entries": [
    {
      "site_name": "pauper-challenge-32-2025-07-1312802837",
      "tournament": "Pauper Challenge 32",
      "date": "2025-07-13",
      "player": "DefNot",
      "archetype": "White Weenie",
      "colors": [
        "W"
      ],
      "record": "2-2",
      "final_rank": 30,
      "source": "mtgo",
      "type": "challenge"
    }
  ]
}
