{
  "username": "snowboy",
  "display_name": "Snowboy",
  "irl_name": null,
  "stats": {
    "total_entries": 5,
    "league_trophies": 5,
    "league_trophies_yearly": 5,
    "challenge_wins": 0,
    "challenge_losses": 0,
    "irl_top8": 0,
    "challenge_win_pct": null,
    "league_trophy_rank_yearly": 224,
    "league_trophy_rank_alltime": 506,
    "league_trophy_players_yearly": 1217,
    "league_trophy_players_alltime": 1958
  },
  "favorite_decks": [
    {
      "archetype": "Spy",
      "count": 5
    }
  ],
  "recent_entries": [
    {
      "site_name": "pauper-league-2026-05-1010636",
      "tournament": "Pauper League",
      "date": "2026-05-10",
      "player": "Snowboy",
      "archetype": "Spy",
      "colors": [
        "B",
        "G",
        "R"
      ],
      "record": "5-0",
      "final_rank": null,
      "source": "mtgo",
      "type": "league"
    },
    {
      "site_name": "pauper-league-2026-05-0310636",
      "tournament": "Pauper League",
      "date": "2026-05-03",
      "player": "Snowboy",
      "archetype": "Spy",
      "colors": [
        "B",
        "G",
        "R"
      ],
      "record": "5-0",
      "final_rank": null,
      "source": "mtgo",
      "type": "league"
    },
    {
      "site_name": "pauper-league-2026-04-2610636",
      "tournament": "Pauper League",
      "date": "2026-04-26",
      "player": "Snowboy",
      "archetype": "Spy",
      "colors": [
        "B",
        "G",
        "R"
      ],
      "record": "5-0",
      "final_rank": null,
      "source": "mtgo",
      "type": "league"
    },
    {
      "site_name": "pauper-league-2026-04-1710405",
      "tournament": "Pauper League",
      "date": "2026-04-17",
      "player": "Snowboy",
      "archetype": "Spy",
      "colors": [
        "B",
        "G",
        "R"
      ],
      "record": "5-0",
      "final_rank": null,
      "source": "mtgo",
      "type": "league"
    },
    {
      "site_name": "pauper-league-2026-02-2710636",
      "tournament": "Pauper League",
      "date": "2026-02-27",
      "player": "Snowboy",
      "archetype": "Spy",
      "colors": [
        "B",
        "G",
        "R"
      ],
      "record": "5-0",
      "final_rank": null,
      "source": "mtgo",
      "type": "league"
    }
  ]
}
