{
  "username": "syns",
  "display_name": "Syns",
  "irl_name": null,
  "stats": {
    "total_entries": 65,
    "league_trophies": 17,
    "league_trophies_yearly": 14,
    "challenge_wins": 165,
    "challenge_losses": 119,
    "irl_top8": 0,
    "challenge_win_pct": 58,
    "league_trophy_rank_yearly": 60,
    "league_trophy_rank_alltime": 130,
    "league_trophy_players_yearly": 1340,
    "league_trophy_players_alltime": 2051
  },
  "favorite_decks": [
    {
      "archetype": "R Madness",
      "count": 45
    },
    {
      "archetype": "Rally",
      "count": 7
    },
    {
      "archetype": "Monster Tron",
      "count": 4
    },
    {
      "archetype": "Pingers",
      "count": 3
    },
    {
      "archetype": "Affinity",
      "count": 2
    },
    {
      "archetype": "BR Madness",
      "count": 2
    },
    {
      "archetype": "U Terror",
      "count": 1
    },
    {
      "archetype": "RG Ponza",
      "count": 1
    }
  ],
  "recent_entries": [
    {
      "site_name": "pauper-league-2026-07-2210855",
      "tournament": "Pauper League",
      "date": "2026-07-22",
      "player": "Syns",
      "archetype": "Monster Tron",
      "colors": [
        "G",
        "R"
      ],
      "record": "5-0",
      "final_rank": null,
      "source": "mtgo",
      "type": "league"
    },
    {
      "site_name": "pauper-last-chance-2026-07-2212847741",
      "tournament": "Pauper Last Chance",
      "date": "2026-07-22",
      "player": "Syns",
      "archetype": "BR Madness",
      "colors": [
        "B",
        "R",
        "U"
      ],
      "record": "4-1",
      "final_rank": null,
      "source": "mtgo",
      "type": "other"
    },
    {
      "site_name": "pauper-last-chance-2026-07-2112847738",
      "tournament": "Pauper Last Chance",
      "date": "2026-07-21",
      "player": "Syns",
      "archetype": "Monster Tron",
      "colors": [
        "G",
        "R"
      ],
      "record": "2-3",
      "final_rank": null,
      "source": "mtgo",
      "type": "other"
    },
    {
      "site_name": "pauper-last-chance-2026-07-2112847730",
      "tournament": "Pauper Last Chance",
      "date": "2026-07-21",
      "player": "Syns",
      "archetype": "Rally",
      "colors": [
        "G",
        "R"
      ],
      "record": "0-4",
      "final_rank": null,
      "source": "mtgo",
      "type": "other"
    },
    {
      "site_name": "pauper-challenge-32-2026-07-1712847682",
      "tournament": "Pauper Challenge 32",
      "date": "2026-07-17",
      "player": "Syns",
      "archetype": "R Madness",
      "colors": [
        "B",
        "R",
        "U"
      ],
      "record": "7-1",
      "final_rank": 3,
      "source": "mtgo",
      "type": "challenge"
    },
    {
      "site_name": "pauper-challenge-32-2026-07-1612847682",
      "tournament": "Pauper Challenge 32",
      "date": "2026-07-17",
      "player": "Syns",
      "archetype": "R Madness",
      "colors": [
        "B",
        "R",
        "U"
      ],
      "record": "7-1",
      "final_rank": 3,
      "source": "mtgo",
      "type": "challenge"
    },
    {
      "site_name": "pauper-challenge-32-2026-07-1512847682",
      "tournament": "Pauper Challenge 32",
      "date": "2026-07-17",
      "player": "Syns",
      "archetype": "R Madness",
      "colors": [
        "B",
        "R",
        "U"
      ],
      "record": "7-1",
      "final_rank": 3,
      "source": "mtgo",
      "type": "challenge"
    },
    {
      "site_name": "pauper-challenge-32-2026-07-1112847128",
      "tournament": "Pauper Challenge 32",
      "date": "2026-07-11",
      "player": "Syns",
      "archetype": "Monster Tron",
      "colors": [
        "G",
        "R"
      ],
      "record": "2-4",
      "final_rank": 31,
      "source": "mtgo",
      "type": "challenge"
    },
    {
      "site_name": "pauper-challenge-32-2026-07-0812846623",
      "tournament": "Pauper Challenge 32",
      "date": "2026-07-08",
      "player": "Syns",
      "archetype": "R Madness",
      "colors": [
        "B",
        "R",
        "U"
      ],
      "record": "3-3",
      "final_rank": 25,
      "source": "mtgo",
      "type": "challenge"
    },
    {
      "site_name": "pauper-league-2026-07-0810855",
      "tournament": "Pauper League",
      "date": "2026-07-08",
      "player": "Syns",
      "archetype": "Affinity",
      "colors": [
        "B",
        "R",
        "U"
      ],
      "record": "5-0",
      "final_rank": null,
      "source": "mtgo",
      "type": "league"
    },
    {
      "site_name": "pauper-challenge-32-2026-07-0612846623",
      "tournament": "Pauper Challenge 32",
      "date": "2026-07-08",
      "player": "Syns",
      "archetype": "R Madness",
      "colors": [
        "B",
        "R",
        "U"
      ],
      "record": "3-3",
      "final_rank": 25,
      "source": "mtgo",
      "type": "challenge"
    },
    {
      "site_name": "pauper-challenge-32-2026-07-0212846460",
      "tournament": "Pauper Challenge 32",
      "date": "2026-07-02",
      "player": "Syns",
      "archetype": "U Terror",
      "colors": [
        "R",
        "U"
      ],
      "record": "4-2",
      "final_rank": 17,
      "source": "mtgo",
      "type": "challenge"
    },
    {
      "site_name": "pauper-challenge-32-2026-06-2512845643",
      "tournament": "Pauper Challenge 32",
      "date": "2026-06-25",
      "player": "Syns",
      "archetype": "Rally",
      "colors": [
        "R"
      ],
      "record": "4-2",
      "final_rank": 13,
      "source": "mtgo",
      "type": "challenge"
    },
    {
      "site_name": "pauper-challenge-32-2026-06-2412845643",
      "tournament": "Pauper Challenge 32",
      "date": "2026-06-25",
      "player": "Syns",
      "archetype": "Rally",
      "colors": [
        "R"
      ],
      "record": "4-2",
      "final_rank": 13,
      "source": "mtgo",
      "type": "challenge"
    },
    {
      "site_name": "pauper-challenge-32-2026-06-2112844875",
      "tournament": "Pauper Challenge 32",
      "date": "2026-06-21",
      "player": "Syns",
      "archetype": "Monster Tron",
      "colors": [
        "G",
        "R",
        "U"
      ],
      "record": "6-3",
      "final_rank": 4,
      "source": "mtgo",
      "type": "challenge"
    },
    {
      "site_name": "pauper-challenge-32-2026-06-2012844856",
      "tournament": "Pauper Challenge 32",
      "date": "2026-06-20",
      "player": "Syns",
      "archetype": "R Madness",
      "colors": [
        "B",
        "R",
        "U"
      ],
      "record": "2-4",
      "final_rank": 31,
      "source": "mtgo",
      "type": "challenge"
    },
    {
      "site_name": "pauper-challenge-32-2025-03-1712844320",
      "tournament": "Pauper Challenge 32",
      "date": "2026-06-13",
      "player": "Syns",
      "archetype": "R Madness",
      "colors": [
        "B",
        "R",
        "U"
      ],
      "record": "3-3",
      "final_rank": 20,
      "source": "mtgo",
      "type": "challenge"
    },
    {
      "site_name": "pauper-challenge-32-2026-06-1312844320",
      "tournament": "Pauper Challenge 32",
      "date": "2026-06-13",
      "player": "Syns",
      "archetype": "R Madness",
      "colors": [
        "B",
        "R",
        "U"
      ],
      "record": "3-3",
      "final_rank": 20,
      "source": "mtgo",
      "type": "challenge"
    },
    {
      "site_name": "pauper-challenge-32-2026-06-1212844305",
      "tournament": "Pauper Challenge 32",
      "date": "2026-06-12",
      "player": "Syns",
      "archetype": "R Madness",
      "colors": [
        "B",
        "R",
        "U"
      ],
      "record": "3-3",
      "final_rank": 28,
      "source": "mtgo",
      "type": "challenge"
    },
    {
      "site_name": "pauper-challenge-32-2026-05-2812843381",
      "tournament": "Pauper Challenge 32",
      "date": "2026-05-28",
      "player": "Syns",
      "archetype": "R Madness",
      "colors": [
        "B",
        "R",
        "U"
      ],
      "record": "2-4",
      "final_rank": 28,
      "source": "mtgo",
      "type": "challenge"
    },
    {
      "site_name": "pauper-challenge-32-2026-05-2312842916",
      "tournament": "Pauper Challenge 32",
      "date": "2026-05-23",
      "player": "Syns",
      "archetype": "R Madness",
      "colors": [
        "B",
        "R",
        "U"
      ],
      "record": "3-3",
      "final_rank": 19,
      "source": "mtgo",
      "type": "challenge"
    },
    {
      "site_name": "pauper-league-2026-05-2210636",
      "tournament": "Pauper League",
      "date": "2026-05-22",
      "player": "Syns",
      "archetype": "R Madness",
      "colors": [
        "B",
        "R",
        "U"
      ],
      "record": "5-0",
      "final_rank": null,
      "source": "mtgo",
      "type": "league"
    },
    {
      "site_name": "pauper-challenge-32-2026-05-1612842489",
      "tournament": "Pauper Challenge 32",
      "date": "2026-05-16",
      "player": "Syns",
      "archetype": "R Madness",
      "colors": [
        "B",
        "R",
        "U"
      ],
      "record": "2-4",
      "final_rank": 30,
      "source": "mtgo",
      "type": "challenge"
    },
    {
      "site_name": "pauper-league-2026-05-0910636",
      "tournament": "Pauper League",
      "date": "2026-05-09",
      "player": "Syns",
      "archetype": "R Madness",
      "colors": [
        "B",
        "R",
        "U"
      ],
      "record": "5-0",
      "final_rank": null,
      "source": "mtgo",
      "type": "league"
    },
    {
      "site_name": "pauper-league-2026-05-0310636",
      "tournament": "Pauper League",
      "date": "2026-05-03",
      "player": "Syns",
      "archetype": "R Madness",
      "colors": [
        "B",
        "R",
        "U"
      ],
      "record": "5-0",
      "final_rank": null,
      "source": "mtgo",
      "type": "league"
    }
  ]
}
