{
  "username": "xxsystemxx",
  "display_name": "xxSystemxx",
  "irl_name": null,
  "stats": {
    "total_entries": 44,
    "league_trophies": 29,
    "league_trophies_yearly": 0,
    "challenge_wins": 67,
    "challenge_losses": 30,
    "irl_top8": 0,
    "challenge_win_pct": 69,
    "league_trophy_rank_yearly": null,
    "league_trophy_rank_alltime": 45,
    "league_trophy_players_yearly": 793,
    "league_trophy_players_alltime": 1890
  },
  "favorite_decks": [
    {
      "archetype": "U",
      "count": 35
    },
    {
      "archetype": "RU",
      "count": 4
    },
    {
      "archetype": "Gardens",
      "count": 2
    },
    {
      "archetype": "W Heroic",
      "count": 1
    },
    {
      "archetype": "Monsters",
      "count": 1
    },
    {
      "archetype": "GU",
      "count": 1
    }
  ],
  "recent_entries": [
    {
      "site_name": "pauper-challenge-32-2025-11-2112824780",
      "tournament": "Pauper Challenge 32",
      "date": "2025-11-21",
      "player": "xxSystemxx",
      "archetype": "Gardens",
      "colors": [
        "B",
        "G"
      ],
      "record": "3-3",
      "final_rank": 23,
      "source": "mtgo",
      "type": "challenge"
    },
    {
      "site_name": "pauper-challenge-32-2025-11-2012824768",
      "tournament": "Pauper Challenge 32",
      "date": "2025-11-20",
      "player": "xxSystemxx",
      "archetype": "Gardens",
      "colors": [
        "B",
        "G",
        "R"
      ],
      "record": "2-2",
      "final_rank": 27,
      "source": "mtgo",
      "type": "challenge"
    },
    {
      "site_name": "pauper-challenge-32-2025-11-0812823572",
      "tournament": "Pauper Challenge 32",
      "date": "2025-11-08",
      "player": "xxSystemxx",
      "archetype": "",
      "colors": [
        "U"
      ],
      "record": "3-3",
      "final_rank": 23,
      "source": "mtgo",
      "type": "challenge"
    },
    {
      "site_name": "pauper-challenge-32-2025-11-0112822687",
      "tournament": "Pauper Challenge 32",
      "date": "2025-11-01",
      "player": "xxSystemxx",
      "archetype": "",
      "colors": [
        "U"
      ],
      "record": "7-2",
      "final_rank": 1,
      "source": "mtgo",
      "type": "challenge"
    },
    {
      "site_name": "pauper-challenge-32-2025-10-1812820716",
      "tournament": "Pauper Challenge 32",
      "date": "2025-10-18",
      "player": "xxSystemxx",
      "archetype": "",
      "colors": [
        "U"
      ],
      "record": "4-2",
      "final_rank": 11,
      "source": "mtgo",
      "type": "challenge"
    },
    {
      "site_name": "pauper-challenge-32-2025-10-1112819523",
      "tournament": "Pauper Challenge 32",
      "date": "2025-10-11",
      "player": "xxSystemxx",
      "archetype": "",
      "colors": [
        "U"
      ],
      "record": "8-1",
      "final_rank": 1,
      "source": "mtgo",
      "type": "challenge"
    },
    {
      "site_name": "pauper-challenge-32-2025-09-2612816520",
      "tournament": "Pauper Challenge 32",
      "date": "2025-09-26",
      "player": "xxSystemxx",
      "archetype": "",
      "colors": [
        "U"
      ],
      "record": "4-2",
      "final_rank": 13,
      "source": "mtgo",
      "type": "challenge"
    },
    {
      "site_name": "pauper-challenge-32-2025-09-1912815119",
      "tournament": "Pauper Challenge 32",
      "date": "2025-09-19",
      "player": "xxSystemxx",
      "archetype": "",
      "colors": [
        "R",
        "U"
      ],
      "record": "2-2",
      "final_rank": 32,
      "source": "mtgo",
      "type": "challenge"
    },
    {
      "site_name": "pauper-challenge-32-2025-09-0612813561",
      "tournament": "Pauper Challenge 32",
      "date": "2025-09-06",
      "player": "xxSystemxx",
      "archetype": "",
      "colors": [
        "U"
      ],
      "record": "3-2",
      "final_rank": 21,
      "source": "mtgo",
      "type": "challenge"
    },
    {
      "site_name": "pauper-challenge-32-2025-09-0512813547",
      "tournament": "Pauper Challenge 32",
      "date": "2025-09-05",
      "player": "xxSystemxx",
      "archetype": "",
      "colors": [
        "R",
        "U"
      ],
      "record": "4-3",
      "final_rank": 7,
      "source": "mtgo",
      "type": "challenge"
    },
    {
      "site_name": "pauper-challenge-32-2025-08-3012812783",
      "tournament": "Pauper Challenge 32",
      "date": "2025-08-30",
      "player": "xxSystemxx",
      "archetype": "",
      "colors": [
        "U"
      ],
      "record": "4-2",
      "final_rank": 17,
      "source": "mtgo",
      "type": "challenge"
    },
    {
      "site_name": "pauper-challenge-32-2025-08-2412812181",
      "tournament": "Pauper Challenge 32",
      "date": "2025-08-24",
      "player": "xxSystemxx",
      "archetype": "",
      "colors": [
        "U"
      ],
      "record": "9-0",
      "final_rank": 1,
      "source": "mtgo",
      "type": "challenge"
    },
    {
      "site_name": "pauper-challenge-32-2025-05-2512782331",
      "tournament": "Pauper Challenge 32",
      "date": "2025-05-25",
      "player": "xxSystemxx",
      "archetype": "",
      "colors": [
        "U"
      ],
      "record": "5-2",
      "final_rank": 9,
      "source": "mtgo",
      "type": "challenge"
    },
    {
      "site_name": "pauper-challenge-32-2025-05-1712780149",
      "tournament": "Pauper Challenge 32",
      "date": "2025-05-17",
      "player": "xxSystemxx",
      "archetype": "",
      "colors": [
        "U"
      ],
      "record": "5-2",
      "final_rank": 5,
      "source": "mtgo",
      "type": "challenge"
    },
    {
      "site_name": "pauper-challenge-32-2025-05-1112777364",
      "tournament": "Pauper Challenge 32",
      "date": "2025-05-11",
      "player": "xxSystemxx",
      "archetype": "",
      "colors": [
        "U"
      ],
      "record": "4-2",
      "final_rank": 14,
      "source": "mtgo",
      "type": "challenge"
    },
    {
      "site_name": "pauper-league-2025-06-099081",
      "tournament": "pauper-league-2025-06-099081",
      "date": "",
      "player": "xxSystemxx",
      "archetype": "",
      "colors": [
        "U"
      ],
      "record": "5-0",
      "final_rank": null,
      "source": "mtgo",
      "type": "league"
    },
    {
      "site_name": "pauper-league-2025-11-179750",
      "tournament": "pauper-league-2025-11-179750",
      "date": "",
      "player": "xxSystemxx",
      "archetype": "W Heroic",
      "colors": [
        "R",
        "W"
      ],
      "record": "5-0",
      "final_rank": null,
      "source": "mtgo",
      "type": "league"
    },
    {
      "site_name": "pauper-league-2025-11-219987",
      "tournament": "pauper-league-2025-11-219987",
      "date": "",
      "player": "xxSystemxx",
      "archetype": "Monsters",
      "colors": [
        "G",
        "R"
      ],
      "record": "5-0",
      "final_rank": null,
      "source": "mtgo",
      "type": "league"
    },
    {
      "site_name": "pauper-league-2025-10-279750",
      "tournament": "pauper-league-2025-10-279750",
      "date": "",
      "player": "xxSystemxx",
      "archetype": "",
      "colors": [
        "U"
      ],
      "record": "5-0",
      "final_rank": null,
      "source": "mtgo",
      "type": "league"
    },
    {
      "site_name": "pauper-league-2025-05-189081",
      "tournament": "pauper-league-2025-05-189081",
      "date": "",
      "player": "xxSystemxx",
      "archetype": "",
      "colors": [
        "U"
      ],
      "record": "5-0",
      "final_rank": null,
      "source": "mtgo",
      "type": "league"
    },
    {
      "site_name": "pauper-league-2025-06-269366",
      "tournament": "pauper-league-2025-06-269366",
      "date": "",
      "player": "xxSystemxx",
      "archetype": "",
      "colors": [
        "U"
      ],
      "record": "5-0",
      "final_rank": null,
      "source": "mtgo",
      "type": "league"
    },
    {
      "site_name": "pauper-league-2025-05-069081",
      "tournament": "pauper-league-2025-05-069081",
      "date": "",
      "player": "xxSystemxx",
      "archetype": "",
      "colors": [
        "U"
      ],
      "record": "5-0",
      "final_rank": null,
      "source": "mtgo",
      "type": "league"
    },
    {
      "site_name": "pauper-league-2025-06-189366",
      "tournament": "pauper-league-2025-06-189366",
      "date": "",
      "player": "xxSystemxx",
      "archetype": "",
      "colors": [
        "R",
        "U"
      ],
      "record": "5-0",
      "final_rank": null,
      "source": "mtgo",
      "type": "league"
    },
    {
      "site_name": "pauper-league-2025-06-189366",
      "tournament": "pauper-league-2025-06-189366",
      "date": "",
      "player": "xxSystemxx",
      "archetype": "",
      "colors": [
        "R",
        "U"
      ],
      "record": "5-0",
      "final_rank": null,
      "source": "mtgo",
      "type": "league"
    },
    {
      "site_name": "pauper-league-2025-06-089081",
      "tournament": "pauper-league-2025-06-089081",
      "date": "",
      "player": "xxSystemxx",
      "archetype": "",
      "colors": [
        "U"
      ],
      "record": "5-0",
      "final_rank": null,
      "source": "mtgo",
      "type": "league"
    }
  ]
}
