{
  "username": "zimooo2",
  "display_name": "zimooo2",
  "irl_name": null,
  "stats": {
    "total_entries": 5,
    "league_trophies": 4,
    "league_trophies_yearly": 0,
    "challenge_wins": 3,
    "challenge_losses": 3,
    "irl_top8": 0,
    "challenge_win_pct": 50,
    "league_trophy_rank_yearly": null,
    "league_trophy_rank_alltime": 623,
    "league_trophy_players_yearly": 793,
    "league_trophy_players_alltime": 1890
  },
  "favorite_decks": [
    {
      "archetype": "Walls",
      "count": 3
    },
    {
      "archetype": "U Terror",
      "count": 2
    }
  ],
  "recent_entries": [
    {
      "site_name": "pauper-challenge-32-2026-06-1412844338",
      "tournament": "Pauper Challenge 32",
      "date": "2026-06-14",
      "player": "zimooo2",
      "archetype": "Walls",
      "colors": [
        "B",
        "G",
        "R",
        "U",
        "W"
      ],
      "record": "3-3",
      "final_rank": 29,
      "source": "mtgo",
      "type": "challenge"
    },
    {
      "site_name": "pauper-league-2025-07-139366",
      "tournament": "pauper-league-2025-07-139366",
      "date": "",
      "player": "zimooo2",
      "archetype": "Walls",
      "colors": [
        "B",
        "G",
        "R",
        "U",
        "W"
      ],
      "record": "5-0",
      "final_rank": null,
      "source": "mtgo",
      "type": "league"
    },
    {
      "site_name": "pauper-league-2025-08-109535",
      "tournament": "pauper-league-2025-08-109535",
      "date": "",
      "player": "zimooo2",
      "archetype": "U Terror",
      "colors": [
        "R",
        "U"
      ],
      "record": "5-0",
      "final_rank": null,
      "source": "mtgo",
      "type": "league"
    },
    {
      "site_name": "pauper-league-2025-07-179366",
      "tournament": "pauper-league-2025-07-179366",
      "date": "",
      "player": "zimooo2",
      "archetype": "Walls",
      "colors": [
        "B",
        "G",
        "R",
        "U",
        "W"
      ],
      "record": "5-0",
      "final_rank": null,
      "source": "mtgo",
      "type": "league"
    },
    {
      "site_name": "pauper-league-2025-08-099535",
      "tournament": "pauper-league-2025-08-099535",
      "date": "",
      "player": "zimooo2",
      "archetype": "U Terror",
      "colors": [
        "R",
        "U"
      ],
      "record": "5-0",
      "final_rank": null,
      "source": "mtgo",
      "type": "league"
    }
  ]
}
